pyfil.py
pyfil-1.10.0.dist-info/entry_points.txt
pyfil-1.10.0.dist-info/LICENSE
pyfil-1.10.0.dist-info/WHEEL
pyfil-1.10.0.dist-info/METADATA
pyfil-1.10.0.dist-info/RECORD
